{
    "COMPONENT_VERSION_BUILD": {
        "description": "Build of components",
        "value": "v1.2.6"
    },
    "COMPONENT_VERSION_DEPLOY": {
        "description": "Deploy of components",
        "value": "v1.1.2"
    },
    "COMPONENT_VERSION_INTEGRATION_TEST": {
        "description": "Integration test of components",
        "value": "v1.0.1"
    },
    "COMPONENT_VERSION_PUBLISH": {
        "description": "Publish of components",
        "value": "v1.1.1"
    },
    "COMPONENT_VERSION_SAST": {
        "description": "SAST of components",
        "value": "v1.0.1"
    },
    "COMPONENT_VERSION_UNIT_TEST": {
        "description": "Unit test of components",
        "value": "v1.1.1"
    },
    "COMPONENT_VERSION_VALIDATE": {
        "description": "Validate of components",
        "value": "v1.3.1"
    },
    "COMPONENT_VERSION_VERSIONING": {
        "description": "Versioning of components",
        "value": "v1.0.1"
    },
    "CONTAINER_IMAGE_ANSIBLE": {
        "description": "container image version with ansible",
        "value": "registry.gitlab.com/pl.rachuna-net/containers/ansible:1.0.0"
    },
    "CONTAINER_IMAGE_BUILD": {
        "description": "container image version with build",
        "value": "docker:24"
    },
    "CONTAINER_IMAGE_MKDOCS": {
        "description": "container image version with mkdocs",
        "value": "registry.gitlab.com/pl.rachuna-net/containers/mkdocs:1.0.0"
    },
    "CONTAINER_IMAGE_PACKER": {
        "description": "container image version with packer",
        "value": "registry.gitlab.com/pl.rachuna-net/containers/packer:1.0.0"
    },
    "CONTAINER_IMAGE_PYTHON": {
        "description": "container image version with python",
        "value": "registry.gitlab.com/pl.rachuna-net/containers/python:1.0.0"
    },
    "CONTAINER_IMAGE_SEMANTIC_RELEASE": {
        "description": "container image version vith semantic-release",
        "value": "registry.gitlab.com/pl.rachuna-net/containers/semantic-release:1.0.0"
    },
    "CONTAINER_IMAGE_SONAR_SCANNER": {
        "description": "container image version with sonar-scanner",
        "value": "registry.gitlab.com/pl.rachuna-net/containers/sonar-scanner:1.0.0"
    },
    "CONTAINER_IMAGE_TERRAFORM": {
        "description": "container image version vith semantic-release",
        "value": "registry.gitlab.com/pl.rachuna-net/containers/terraform:1.0.0"
    },
    "SONAR_HOST_URL": {
        "description": "SonarQube host URL",
        "value": "https://sonarcloud.io"
    },
    "SONAR_ORGANIZATION": {
        "description": "SonarQube organization",
        "value": "pl-rachuna-net"
    }
}